Workbook

Sheet Resumo
A1: Resumo do Cálculo
A2: Nome do Segurado: | B2: SEGURADO EXEMPLO | D2: NIT: | E2: 000.00000.00-0
A3: CPF: | B3: 000.000.000-00 | D3: Data de Nascimento: | E3: 13/08/1976
A4: Sexo: | B4: Masculino | D4: Nº do Benefício: | E4: 000.000.000-0
A5: Espécie do Benefício: | B5: 46 - Aposentadoria Especial | D5: Nº do Processo: | E5: 0000000-00.2021.4.01.3800
A6: Início do Benefício (DIB): | B6: 16/10/2019 | D6: Data da Atualização: | E6: 08/05/2025
A7: Ajuizamento: | B7: 21/01/2021 | D7: Data da Prescrição: | E7: 16/10/2019
A9: Renda Mensal Corrigida até 08/05/2025: | B9: ='Diferenças'!B93
A10: Principal: | B10: ='Diferenças'!D91
A11: Correção Monetária: | B11: ='Diferenças'!M91-'Diferenças'!D91
A12: Total Atualizado: | B12: ='Diferenças'!M91
A13: Valor dos Juros: | B13: ='Diferenças'!N91
A14: (-) Acordo/Deságio: | B14: ='Parâmetros'!$B$24
A15: Total Atualizado + Valor dos Juros - Valor Acordo: | B15: =B12+B13-B14
A16: Honorários Sobre a Base de Cálculo Atualizada: | B16: ='Honorários'!$B$90
A17: Honorários Sobre os Juros da Base de Cálculo: | B17: ='Honorários'!$B$91
A18: Valor Fixo de Honorários: | B18: ='Honorários'!$B$92
A19: Total Atualizado de Honorários: | B19: ='Honorários'!$B$93
A20: Multa: | B20: ='Parâmetros'!$B$25
A21: Dano Moral/Material: | B21: ='Parâmetros'!$B$26
A22: Total Geral: | B22: =B15+B19+B20+B21
A23: Total geral atualizado até 08/05/2025
A24: O valor equivale a (salários mínimos): | B24: =ROUND(B22/'Parâmetros'!$B$27,2)
A26: Valor da causa (art. 292, §§ 1º e 2º, do CPC)
A27: Parcelas vencidas (atualizadas + juros): | B27: =B15
A28: 12 parcelas vincendas (12 × R.M.A.): | B28: =ROUND(12*'Diferenças'!B93,2)
A29: Valor da causa: | B29: =B27+B28
A30: Limite do JEF (60 salários mínimos): | B30: =ROUND(60*'Parâmetros'!$B$27,2)
A31: Competência: | B31: =IF(B29<=B30,"Juizado Especial Federal","Vara Federal (ou renúncia ao excedente)")
A34: Cristiano da Silva Ottone OAB/MG 152.214

Sheet Parâmetros
A1: Parâmetros do cálculo (células amarelas podem ser editadas)
A3: Nome do segurado | B3: SEGURADO EXEMPLO
A4: NIT | B4: 000.00000.00-0
A5: CPF | B5: 000.000.000-00
A6: Data de nascimento | B6: 13/08/1976
A7: Sexo | B7: M
A8: Nº do benefício | B8: 000.000.000-0
A9: Espécie | B9: 46 - Aposentadoria Especial
A10: DER
A11: DIB | B11: 16/10/2019
A12: RMI (renda mensal inicial) | B12: 4119.82
A13: Nº do processo | B13: 0000000-00.2021.4.01.3800
A14: Inscrição no INSS | B14: 02/01/1992
A15: Ajuizamento | B15: 21/01/2021
A16: Citação (início dos juros de mora) | B16: 01/10/2021
A17: Data da prescrição quinquenal | B17: 16/10/2019
A18: Data da atualização | B18: 08/05/2025
A19: Diferenças desde | B19: 16/10/2019
A20: Diferenças até | B20: 28/02/2025
A21: Honorários (%) | B21: 10
A22: Honorários: parcelas até (Súmula 111/STJ) | B22: todas
A23: Honorários: valor fixo | B23: 0
A24: (-) Acordo/Deságio | B24: 0
A25: Multa | B25: 0
A26: Dano moral/material | B26: 0
A27: Salário mínimo na data da atualização | B27: 1518
A28: Índice de correção | B28: INPC
A29: Responsável pelo cálculo | B29: Cristiano da Silva Ottone
A30: OAB | B30: OAB/MG 152.214

Sheet Evolução RMI
A1: Relatório da Evolução da R.M.I.
A2: Nome do Segurado: | B2: SEGURADO EXEMPLO | D2: NIT: | E2: 000.00000.00-0
A3: CPF: | B3: 000.000.000-00 | D3: Data de Nascimento: | E3: 13/08/1976
A4: Sexo: | B4: Masculino | D4: Nº do Benefício: | E4: 000.000.000-0
A5: Espécie do Benefício: | B5: 46 - Aposentadoria Especial | D5: Nº do Processo: | E5: 0000000-00.2021.4.01.3800
A6: Início do Benefício (DIB): | B6: 16/10/2019 | D6: Data da Atualização: | E6: 08/05/2025
A7: Ajuizamento: | B7: 21/01/2021 | D7: Data da Prescrição: | E7: 16/10/2019
A9: Data | B9: Valor do Benefício | C9: Reajuste (%) | D9: Teto do Benefício | E9: Salário Mínimo | F9: Benefício Mensal | G9: Fração (pró-rata) | H9: Benefício Considerado
A10: 10/2019 | B10: ='Parâmetros'!$B$12 | D10: 5839.45 | E10: 998 | F10: =MAX(E10,MIN(D10,IF(C10="",B10,TRUNC(B10*(1+C10/100),2)))) | G10: 0.5 | H10: =TRUNC(F10*G10,2)
A11: 11/2019 | B11: =F10 | D11: 5839.45 | E11: 998 | F11: =MAX(E11,MIN(D11,IF(C11="",B11,TRUNC(B11*(1+C11/100),2)))) | G11: 1 | H11: =TRUNC(F11*G11,2)
A12: 12/2019 | B12: =F11 | D12: 5839.45 | E12: 998 | F12: =MAX(E12,MIN(D12,IF(C12="",B12,TRUNC(B12*(1+C12/100),2)))) | G12: 1 | H12: =TRUNC(F12*G12,2)
A13: 01/2020 | B13: =F12 | C13: 1.81 | D13: 6101.06 | E13: 1039 | F13: =MAX(E13,MIN(D13,IF(C13="",B13,TRUNC(B13*(1+C13/100),2)))) | G13: 1 | H13: =TRUNC(F13*G13,2)
A14: 02/2020 | B14: =F13 | D14: 6101.06 | E14: 1045 | F14: =MAX(E14,MIN(D14,IF(C14="",B14,TRUNC(B14*(1+C14/100),2)))) | G14: 1 | H14: =TRUNC(F14*G14,2)
A15: 03/2020 | B15: =F14 | D15: 6101.06 | E15: 1045 | F15: =MAX(E15,MIN(D15,IF(C15="",B15,TRUNC(B15*(1+C15/100),2)))) | G15: 1 | H15: =TRUNC(F15*G15,2)
A16: 04/2020 | B16: =F15 | D16: 6101.06 | E16: 1045 | F16: =MAX(E16,MIN(D16,IF(C16="",B16,TRUNC(B16*(1+C16/100),2)))) | G16: 1 | H16: =TRUNC(F16*G16,2)
A17: 05/2020 | B17: =F16 | D17: 6101.06 | E17: 1045 | F17: =MAX(E17,MIN(D17,IF(C17="",B17,TRUNC(B17*(1+C17/100),2)))) | G17: 1 | H17: =TRUNC(F17*G17,2)
A18: 06/2020 | B18: =F17 | D18: 6101.06 | E18: 1045 | F18: =MAX(E18,MIN(D18,IF(C18="",B18,TRUNC(B18*(1+C18/100),2)))) | G18: 1 | H18: =TRUNC(F18*G18,2)
A19: 07/2020 | B19: =F18 | D19: 6101.06 | E19: 1045 | F19: =MAX(E19,MIN(D19,IF(C19="",B19,TRUNC(B19*(1+C19/100),2)))) | G19: 1 | H19: =TRUNC(F19*G19,2)
A20: 08/2020 | B20: =F19 | D20: 6101.06 | E20: 1045 | F20: =MAX(E20,MIN(D20,IF(C20="",B20,TRUNC(B20*(1+C20/100),2)))) | G20: 1 | H20: =TRUNC(F20*G20,2)
A21: 09/2020 | B21: =F20 | D21: 6101.06 | E21: 1045 | F21: =MAX(E21,MIN(D21,IF(C21="",B21,TRUNC(B21*(1+C21/100),2)))) | G21: 1 | H21: =TRUNC(F21*G21,2)
A22: 10/2020 | B22: =F21 | D22: 6101.06 | E22: 1045 | F22: =MAX(E22,MIN(D22,IF(C22="",B22,TRUNC(B22*(1+C22/100),2)))) | G22: 1 | H22: =TRUNC(F22*G22,2)
A23: 11/2020 | B23: =F22 | D23: 6101.06 | E23: 1045 | F23: =MAX(E23,MIN(D23,IF(C23="",B23,TRUNC(B23*(1+C23/100),2)))) | G23: 1 | H23: =TRUNC(F23*G23,2)
A24: 12/2020 | B24: =F23 | D24: 6101.06 | E24: 1045 | F24: =MAX(E24,MIN(D24,IF(C24="",B24,TRUNC(B24*(1+C24/100),2)))) | G24: 1 | H24: =TRUNC(F24*G24,2)
A25: 01/2021 | B25: =F24 | C25: 5.45 | D25: 6433.57 | E25: 1100 | F25: =MAX(E25,MIN(D25,IF(C25="",B25,TRUNC(B25*(1+C25/100),2)))) | G25: 1 | H25: =TRUNC(F25*G25,2)
A26: 02/2021 | B26: =F25 | D26: 6433.57 | E26: 1100 | F26: =MAX(E26,MIN(D26,IF(C26="",B26,TRUNC(B26*(1+C26/100),2)))) | G26: 1 | H26: =TRUNC(F26*G26,2)
A27: 03/2021 | B27: =F26 | D27: 6433.57 | E27: 1100 | F27: =MAX(E27,MIN(D27,IF(C27="",B27,TRUNC(B27*(1+C27/100),2)))) | G27: 1 | H27: =TRUNC(F27*G27,2)
A28: 04/2021 | B28: =F27 | D28: 6433.57 | E28: 1100 | F28: =MAX(E28,MIN(D28,IF(C28="",B28,TRUNC(B28*(1+C28/100),2)))) | G28: 1 | H28: =TRUNC(F28*G28,2)
A29: 05/2021 | B29: =F28 | D29: 6433.57 | E29: 1100 | F29: =MAX(E29,MIN(D29,IF(C29="",B29,TRUNC(B29*(1+C29/100),2)))) | G29: 1 | H29: =TRUNC(F29*G29,2)
A30: 06/2021 | B30: =F29 | D30: 6433.57 | E30: 1100 | F30: =MAX(E30,MIN(D30,IF(C30="",B30,TRUNC(B30*(1+C30/100),2)))) | G30: 1 | H30: =TRUNC(F30*G30,2)
A31: 07/2021 | B31: =F30 | D31: 6433.57 | E31: 1100 | F31: =MAX(E31,MIN(D31,IF(C31="",B31,TRUNC(B31*(1+C31/100),2)))) | G31: 1 | H31: =TRUNC(F31*G31,2)
A32: 08/2021 | B32: =F31 | D32: 6433.57 | E32: 1100 | F32: =MAX(E32,MIN(D32,IF(C32="",B32,TRUNC(B32*(1+C32/100),2)))) | G32: 1 | H32: =TRUNC(F32*G32,2)
A33: 09/2021 | B33: =F32 | D33: 6433.57 | E33: 1100 | F33: =MAX(E33,MIN(D33,IF(C33="",B33,TRUNC(B33*(1+C33/100),2)))) | G33: 1 | H33: =TRUNC(F33*G33,2)
A34: 10/2021 | B34: =F33 | D34: 6433.57 | E34: 1100 | F34: =MAX(E34,MIN(D34,IF(C34="",B34,TRUNC(B34*(1+C34/100),2)))) | G34: 1 | H34: =TRUNC(F34*G34,2)
A35: 11/2021 | B35: =F34 | D35: 6433.57 | E35: 1100 | F35: =MAX(E35,MIN(D35,IF(C35="",B35,TRUNC(B35*(1+C35/100),2)))) | G35: 1 | H35: =TRUNC(F35*G35,2)
A36: 12/2021 | B36: =F35 | D36: 6433.57 | E36: 1100 | F36: =MAX(E36,MIN(D36,IF(C36="",B36,TRUNC(B36*(1+C36/100),2)))) | G36: 1 | H36: =TRUNC(F36*G36,2)
A37: 01/2022 | B37: =F36 | C37: 10.16 | D37: 7087.22 | E37: 1212 | F37: =MAX(E37,MIN(D37,IF(C37="",B37,TRUNC(B37*(1+C37/100),2)))) | G37: 1 | H37: =TRUNC(F37*G37,2)
A38: 02/2022 | B38: =F37 | D38: 7087.22 | E38: 1212 | F38: =MAX(E38,MIN(D38,IF(C38="",B38,TRUNC(B38*(1+C38/100),2)))) | G38: 1 | H38: =TRUNC(F38*G38,2)
A39: 03/2022 | B39: =F38 | D39: 7087.22 | E39: 1212 | F39: =MAX(E39,MIN(D39,IF(C39="",B39,TRUNC(B39*(1+C39/100),2)))) | G39: 1 | H39: =TRUNC(F39*G39,2)
A40: 04/2022 | B40: =F39 | D40: 7087.22 | E40: 1212 | F40: =MAX(E40,MIN(D40,IF(C40="",B40,TRUNC(B40*(1+C40/100),2)))) | G40: 1 | H40: =TRUNC(F40*G40,2)
A41: 05/2022 | B41: =F40 | D41: 7087.22 | E41: 1212 | F41: =MAX(E41,MIN(D41,IF(C41="",B41,TRUNC(B41*(1+C41/100),2)))) | G41: 1 | H41: =TRUNC(F41*G41,2)
A42: 06/2022 | B42: =F41 | D42: 7087.22 | E42: 1212 | F42: =MAX(E42,MIN(D42,IF(C42="",B42,TRUNC(B42*(1+C42/100),2)))) | G42: 1 | H42: =TRUNC(F42*G42,2)
A43: 07/2022 | B43: =F42 | D43: 7087.22 | E43: 1212 | F43: =MAX(E43,MIN(D43,IF(C43="",B43,TRUNC(B43*(1+C43/100),2)))) | G43: 1 | H43: =TRUNC(F43*G43,2)
A44: 08/2022 | B44: =F43 | D44: 7087.22 | E44: 1212 | F44: =MAX(E44,MIN(D44,IF(C44="",B44,TRUNC(B44*(1+C44/100),2)))) | G44: 1 | H44: =TRUNC(F44*G44,2)
A45: 09/2022 | B45: =F44 | D45: 7087.22 | E45: 1212 | F45: =MAX(E45,MIN(D45,IF(C45="",B45,TRUNC(B45*(1+C45/100),2)))) | G45: 1 | H45: =TRUNC(F45*G45,2)
A46: 10/2022 | B46: =F45 | D46: 7087.22 | E46: 1212 | F46: =MAX(E46,MIN(D46,IF(C46="",B46,TRUNC(B46*(1+C46/100),2)))) | G46: 1 | H46: =TRUNC(F46*G46,2)
A47: 11/2022 | B47: =F46 | D47: 7087.22 | E47: 1212 | F47: =MAX(E47,MIN(D47,IF(C47="",B47,TRUNC(B47*(1+C47/100),2)))) | G47: 1 | H47: =TRUNC(F47*G47,2)
A48: 12/2022 | B48: =F47 | D48: 7087.22 | E48: 1212 | F48: =MAX(E48,MIN(D48,IF(C48="",B48,TRUNC(B48*(1+C48/100),2)))) | G48: 1 | H48: =TRUNC(F48*G48,2)
A49: 01/2023 | B49: =F48 | C49: 5.93 | D49: 7507.49 | E49: 1302 | F49: =MAX(E49,MIN(D49,IF(C49="",B49,TRUNC(B49*(1+C49/100),2)))) | G49: 1 | H49: =TRUNC(F49*G49,2)
A50: 02/2023 | B50: =F49 | D50: 7507.49 | E50: 1302 | F50: =MAX(E50,MIN(D50,IF(C50="",B50,TRUNC(B50*(1+C50/100),2)))) | G50: 1 | H50: =TRUNC(F50*G50,2)
A51: 03/2023 | B51: =F50 | D51: 7507.49 | E51: 1302 | F51: =MAX(E51,MIN(D51,IF(C51="",B51,TRUNC(B51*(1+C51/100),2)))) | G51: 1 | H51: =TRUNC(F51*G51,2)
A52: 04/2023 | B52: =F51 | D52: 7507.49 | E52: 1302 | F52: =MAX(E52,MIN(D52,IF(C52="",B52,TRUNC(B52*(1+C52/100),2)))) | G52: 1 | H52: =TRUNC(F52*G52,2)
A53: 05/2023 | B53: =F52 | D53: 7507.49 | E53: 1320 | F53: =MAX(E53,MIN(D53,IF(C53="",B53,TRUNC(B53*(1+C53/100),2)))) | G53: 1 | H53: =TRUNC(F53*G53,2)
A54: 06/2023 | B54: =F53 | D54: 7507.49 | E54: 1320 | F54: =MAX(E54,MIN(D54,IF(C54="",B54,TRUNC(B54*(1+C54/100),2)))) | G54: 1 | H54: =TRUNC(F54*G54,2)
A55: 07/2023 | B55: =F54 | D55: 7507.49 | E55: 1320 | F55: =MAX(E55,MIN(D55,IF(C55="",B55,TRUNC(B55*(1+C55/100),2)))) | G55: 1 | H55: =TRUNC(F55*G55,2)
A56: 08/2023 | B56: =F55 | D56: 7507.49 | E56: 1320 | F56: =MAX(E56,MIN(D56,IF(C56="",B56,TRUNC(B56*(1+C56/100),2)))) | G56: 1 | H56: =TRUNC(F56*G56,2)
A57: 09/2023 | B57: =F56 | D57: 7507.49 | E57: 1320 | F57: =MAX(E57,MIN(D57,IF(C57="",B57,TRUNC(B57*(1+C57/100),2)))) | G57: 1 | H57: =TRUNC(F57*G57,2)
A58: 10/2023 | B58: =F57 | D58: 7507.49 | E58: 1320 | F58: =MAX(E58,MIN(D58,IF(C58="",B58,TRUNC(B58*(1+C58/100),2)))) | G58: 1 | H58: =TRUNC(F58*G58,2)
A59: 11/2023 | B59: =F58 | D59: 7507.49 | E59: 1320 | F59: =MAX(E59,MIN(D59,IF(C59="",B59,TRUNC(B59*(1+C59/100),2)))) | G59: 1 | H59: =TRUNC(F59*G59,2)
A60: 12/2023 | B60: =F59 | D60: 7507.49 | E60: 1320 | F60: =MAX(E60,MIN(D60,IF(C60="",B60,TRUNC(B60*(1+C60/100),2)))) | G60: 1 | H60: =TRUNC(F60*G60,2)
A61: 01/2024 | B61: =F60 | C61: 3.71 | D61: 7786.02 | E61: 1412 | F61: =MAX(E61,MIN(D61,IF(C61="",B61,TRUNC(B61*(1+C61/100),2)))) | G61: 1 | H61: =TRUNC(F61*G61,2)
A62: 02/2024 | B62: =F61 | D62: 7786.02 | E62: 1412 | F62: =MAX(E62,MIN(D62,IF(C62="",B62,TRUNC(B62*(1+C62/100),2)))) | G62: 1 | H62: =TRUNC(F62*G62,2)
A63: 03/2024 | B63: =F62 | D63: 7786.02 | E63: 1412 | F63: =MAX(E63,MIN(D63,IF(C63="",B63,TRUNC(B63*(1+C63/100),2)))) | G63: 1 | H63: =TRUNC(F63*G63,2)
A64: 04/2024 | B64: =F63 | D64: 7786.02 | E64: 1412 | F64: =MAX(E64,MIN(D64,IF(C64="",B64,TRUNC(B64*(1+C64/100),2)))) | G64: 1 | H64: =TRUNC(F64*G64,2)
A65: 05/2024 | B65: =F64 | D65: 7786.02 | E65: 1412 | F65: =MAX(E65,MIN(D65,IF(C65="",B65,TRUNC(B65*(1+C65/100),2)))) | G65: 1 | H65: =TRUNC(F65*G65,2)
A66: 06/2024 | B66: =F65 | D66: 7786.02 | E66: 1412 | F66: =MAX(E66,MIN(D66,IF(C66="",B66,TRUNC(B66*(1+C66/100),2)))) | G66: 1 | H66: =TRUNC(F66*G66,2)
A67: 07/2024 | B67: =F66 | D67: 7786.02 | E67: 1412 | F67: =MAX(E67,MIN(D67,IF(C67="",B67,TRUNC(B67*(1+C67/100),2)))) | G67: 1 | H67: =TRUNC(F67*G67,2)
A68: 08/2024 | B68: =F67 | D68: 7786.02 | E68: 1412 | F68: =MAX(E68,MIN(D68,IF(C68="",B68,TRUNC(B68*(1+C68/100),2)))) | G68: 1 | H68: =TRUNC(F68*G68,2)
A69: 09/2024 | B69: =F68 | D69: 7786.02 | E69: 1412 | F69: =MAX(E69,MIN(D69,IF(C69="",B69,TRUNC(B69*(1+C69/100),2)))) | G69: 1 | H69: =TRUNC(F69*G69,2)
A70: 10/2024 | B70: =F69 | D70: 7786.02 | E70: 1412 | F70: =MAX(E70,MIN(D70,IF(C70="",B70,TRUNC(B70*(1+C70/100),2)))) | G70: 1 | H70: =TRUNC(F70*G70,2)
A71: 11/2024 | B71: =F70 | D71: 7786.02 | E71: 1412 | F71: =MAX(E71,MIN(D71,IF(C71="",B71,TRUNC(B71*(1+C71/100),2)))) | G71: 1 | H71: =TRUNC(F71*G71,2)
A72: 12/2024 | B72: =F71 | D72: 7786.02 | E72: 1412 | F72: =MAX(E72,MIN(D72,IF(C72="",B72,TRUNC(B72*(1+C72/100),2)))) | G72: 1 | H72: =TRUNC(F72*G72,2)
A73: 01/2025 | B73: =F72 | C73: 4.77 | D73: 8157.41 | E73: 1518 | F73: =MAX(E73,MIN(D73,IF(C73="",B73,TRUNC(B73*(1+C73/100),2)))) | G73: 1 | H73: =TRUNC(F73*G73,2)
A74: 02/2025 | B74: =F73 | D74: 8157.41 | E74: 1518 | F74: =MAX(E74,MIN(D74,IF(C74="",B74,TRUNC(B74*(1+C74/100),2)))) | G74: 1 | H74: =TRUNC(F74*G74,2)
A75: 03/2025 | B75: =F74 | D75: 8157.41 | E75: 1518 | F75: =MAX(E75,MIN(D75,IF(C75="",B75,TRUNC(B75*(1+C75/100),2)))) | G75: 1 | H75: =TRUNC(F75*G75,2)
A76: 04/2025 | B76: =F75 | D76: 8157.41 | E76: 1518 | F76: =MAX(E76,MIN(D76,IF(C76="",B76,TRUNC(B76*(1+C76/100),2)))) | G76: 1 | H76: =TRUNC(F76*G76,2)
A77: 05/2025 | B77: =F76 | D77: 8157.41 | E77: 1518 | F77: =MAX(E77,MIN(D77,IF(C77="",B77,TRUNC(B77*(1+C77/100),2)))) | G77: 1 | H77: =TRUNC(F77*G77,2)
A79: Nova R.M.A.: | B79: =F77
A80: Pró-rata no mês inicial (data da DIB ou da prescrição) e no mês final, proporcional ao número de dias (mês comercial de 30 dias). Valores truncados em centavos. 1º reajuste proporcional ao INPC do mês da DIB a dezembro.

Sheet Diferenças
A1: Relatório das Diferenças Não Recebidas
A2: Nome do Segurado: | B2: SEGURADO EXEMPLO | D2: NIT: | E2: 000.00000.00-0
A3: CPF: | B3: 000.000.000-00 | D3: Data de Nascimento: | E3: 13/08/1976
A4: Sexo: | B4: Masculino | D4: Nº do Benefício: | E4: 000.000.000-0
A5: Espécie do Benefício: | B5: 46 - Aposentadoria Especial | D5: Nº do Processo: | E5: 0000000-00.2021.4.01.3800
A6: Início do Benefício (DIB): | B6: 16/10/2019 | D6: Data da Atualização: | E6: 08/05/2025
A7: Ajuizamento: | B7: 21/01/2021 | D7: Data da Prescrição: | E7: 16/10/2019
A9: Correção monetária: Tabela da Justiça Federal (INPC; IGP-DI de 05/1996 a 08/2006), pró-rata no 1º mês, até 11/2021.
A10: Juros de mora a partir da citação: 1% a.m. até 06/2009; 0,5% a.m. até 04/2012; juros da poupança (Lei 12.703/2012) até 11/2021 — sem capitalização.
A11: De 12/2021 a 08/2025: SELIC acumulada (simples), uma única vez, substituindo correção e juros (EC 113/2021, art. 3º; Tema 1.419/STF).
A12: Diferenças consideradas de 16/10/2019 a 28/02/2025.
A14: Data | B14: Valor do Benefício | C14: Valor Já Recebido | D14: Diferença | E14: Índice de Atualização | F14: Valor Atualizado | G14: % Juros | H14: Valor dos Juros | I14: Valor Atualizado + Juros | J14: % Selic | K14: Valor da Selic | L14: Total Atualizado | M14: Base atualizada | N14: Juros (todos) | O14: Ano | P14: Tipo
A15: 10/2019 | B15: ='Evolução RMI'!H10 | C15: 0 | D15: =B15-C15 | E15: 1.1738057 | F15: =ROUND(D15*E15,2) | G15: 0.7987 | H15: =ROUND(F15*G15/100,2) | I15: =F15+H15 | J15: 39.21 | K15: =ROUND(I15*J15/100,2) | L15: =I15+K15 | M15: =F15 | N15: =H15+K15 | O15: 2019 | P15: mensal
A16: 11/2019 | B16: ='Evolução RMI'!H11 | C16: 0 | D16: =B16-C16 | E16: 1.1735635 | F16: =ROUND(D16*E16,2) | G16: 0.7987 | H16: =ROUND(F16*G16/100,2) | I16: =F16+H16 | J16: 39.21 | K16: =ROUND(I16*J16/100,2) | L16: =I16+K16 | M16: =F16 | N16: =H16+K16 | O16: 2019 | P16: mensal
A17: 12/2019 | B17: ='Evolução RMI'!H12 | C17: 0 | D17: =B17-C17 | E17: 1.1672602 | F17: =ROUND(D17*E17,2) | G17: 0.7987 | H17: =ROUND(F17*G17/100,2) | I17: =F17+H17 | J17: 39.21 | K17: =ROUND(I17*J17/100,2) | L17: =I17+K17 | M17: =F17 | N17: =H17+K17 | O17: 2019 | P17: mensal
A18: 13º | B18: =TRUNC('Evolução RMI'!F12*3/12,2) | C18: 0 | D18: =B18-C18 | E18: 1.1672602 | F18: =ROUND(D18*E18,2) | G18: 0.7987 | H18: =ROUND(F18*G18/100,2) | I18: =F18+H18 | J18: 39.21 | K18: =ROUND(I18*J18/100,2) | L18: =I18+K18 | M18: =F18 | N18: =H18+K18 | O18: 2019 | P18: 13º
A19: 01/2020 | B19: ='Evolução RMI'!H13 | C19: 0 | D19: =B19-C19 | E19: 1.1531913 | F19: =ROUND(D19*E19,2) | G19: 0.7987 | H19: =ROUND(F19*G19/100,2) | I19: =F19+H19 | J19: 39.21 | K19: =ROUND(I19*J19/100,2) | L19: =I19+K19 | M19: =F19 | N19: =H19+K19 | O19: 2020 | P19: mensal
A20: 02/2020 | B20: ='Evolução RMI'!H14 | C20: 0 | D20: =B20-C20 | E20: 1.1510044 | F20: =ROUND(D20*E20,2) | G20: 0.7987 | H20: =ROUND(F20*G20/100,2) | I20: =F20+H20 | J20: 39.21 | K20: =ROUND(I20*J20/100,2) | L20: =I20+K20 | M20: =F20 | N20: =H20+K20 | O20: 2020 | P20: mensal
A21: 03/2020 | B21: ='Evolução RMI'!H15 | C21: 0 | D21: =B21-C21 | E21: 1.149051 | F21: =ROUND(D21*E21,2) | G21: 0.7987 | H21: =ROUND(F21*G21/100,2) | I21: =F21+H21 | J21: 39.21 | K21: =ROUND(I21*J21/100,2) | L21: =I21+K21 | M21: =F21 | N21: =H21+K21 | O21: 2020 | P21: mensal
A22: 04/2020 | B22: ='Evolução RMI'!H16 | C22: 0 | D22: =B22-C22 | E22: 1.1469864 | F22: =ROUND(D22*E22,2) | G22: 0.7987 | H22: =ROUND(F22*G22/100,2) | I22: =F22+H22 | J22: 39.21 | K22: =ROUND(I22*J22/100,2) | L22: =I22+K22 | M22: =F22 | N22: =H22+K22 | O22: 2020 | P22: mensal
A23: 13º | B23: =TRUNC('Evolução RMI'!F16/2,2) | C23: 0 | D23: =B23-C23 | E23: 1.1469864 | F23: =ROUND(D23*E23,2) | G23: 0.7987 | H23: =ROUND(F23*G23/100,2) | I23: =F23+H23 | J23: 39.21 | K23: =ROUND(I23*J23/100,2) | L23: =I23+K23 | M23: =F23 | N23: =H23+K23 | O23: 2020 | P23: 13º
A24: 05/2020 | B24: ='Evolução RMI'!H17 | C24: 0 | D24: =B24-C24 | E24: 1.1496306 | F24: =ROUND(D24*E24,2) | G24: 0.7987 | H24: =ROUND(F24*G24/100,2) | I24: =F24+H24 | J24: 39.21 | K24: =ROUND(I24*J24/100,2) | L24: =I24+K24 | M24: =F24 | N24: =H24+K24 | O24: 2020 | P24: mensal
A25: 13º | B25: =TRUNC('Evolução RMI'!F17*12/12-'Evolução RMI'!F16/2,2) | C25: 0 | D25: =B25-C25 | E25: 1.1496306 | F25: =ROUND(D25*E25,2) | G25: 0.7987 | H25: =ROUND(F25*G25/100,2) | I25: =F25+H25 | J25: 39.21 | K25: =ROUND(I25*J25/100,2) | L25: =I25+K25 | M25: =F25 | N25: =H25+K25 | O25: 2020 | P25: 13º
A26: 06/2020 | B26: ='Evolução RMI'!H18 | C26: 0 | D26: =B26-C26 | E26: 1.1525119 | F26: =ROUND(D26*E26,2) | G26: 0.7987 | H26: =ROUND(F26*G26/100,2) | I26: =F26+H26 | J26: 39.21 | K26: =ROUND(I26*J26/100,2) | L26: =I26+K26 | M26: =F26 | N26: =H26+K26 | O26: 2020 | P26: mensal
A27: 07/2020 | B27: ='Evolução RMI'!H19 | C27: 0 | D27: =B27-C27 | E27: 1.1490647 | F27: =ROUND(D27*E27,2) | G27: 0.7987 | H27: =ROUND(F27*G27/100,2) | I27: =F27+H27 | J27: 39.21 | K27: =ROUND(I27*J27/100,2) | L27: =I27+K27 | M27: =F27 | N27: =H27+K27 | O27: 2020 | P27: mensal
A28: 08/2020 | B28: ='Evolução RMI'!H20 | C28: 0 | D28: =B28-C28 | E28: 1.1440309 | F28: =ROUND(D28*E28,2) | G28: 0.7987 | H28: =ROUND(F28*G28/100,2) | I28: =F28+H28 | J28: 39.21 | K28: =ROUND(I28*J28/100,2) | L28: =I28+K28 | M28: =F28 | N28: =H28+K28 | O28: 2020 | P28: mensal
A29: 09/2020 | B29: ='Evolução RMI'!H21 | C29: 0 | D29: =B29-C29 | E29: 1.1399272 | F29: =ROUND(D29*E29,2) | G29: 0.7987 | H29: =ROUND(F29*G29/100,2) | I29: =F29+H29 | J29: 39.21 | K29: =ROUND(I29*J29/100,2) | L29: =I29+K29 | M29: =F29 | N29: =H29+K29 | O29: 2020 | P29: mensal
A30: 10/2020 | B30: ='Evolução RMI'!H22 | C30: 0 | D30: =B30-C30 | E30: 1.1300954 | F30: =ROUND(D30*E30,2) | G30: 0.7987 | H30: =ROUND(F30*G30/100,2) | I30: =F30+H30 | J30: 39.21 | K30: =ROUND(I30*J30/100,2) | L30: =I30+K30 | M30: =F30 | N30: =H30+K30 | O30: 2020 | P30: mensal
A31: 11/2020 | B31: ='Evolução RMI'!H23 | C31: 0 | D31: =B31-C31 | E31: 1.1201263 | F31: =ROUND(D31*E31,2) | G31: 0.7987 | H31: =ROUND(F31*G31/100,2) | I31: =F31+H31 | J31: 39.21 | K31: =ROUND(I31*J31/100,2) | L31: =I31+K31 | M31: =F31 | N31: =H31+K31 | O31: 2020 | P31: mensal
A32: 12/2020 | B32: ='Evolução RMI'!H24 | C32: 0 | D32: =B32-C32 | E32: 1.1095852 | F32: =ROUND(D32*E32,2) | G32: 0.7987 | H32: =ROUND(F32*G32/100,2) | I32: =F32+H32 | J32: 39.21 | K32: =ROUND(I32*J32/100,2) | L32: =I32+K32 | M32: =F32 | N32: =H32+K32 | O32: 2020 | P32: mensal
A33: 01/2021 | B33: ='Evolução RMI'!H25 | C33: 0 | D33: =B33-C33 | E33: 1.0936184 | F33: =ROUND(D33*E33,2) | G33: 0.7987 | H33: =ROUND(F33*G33/100,2) | I33: =F33+H33 | J33: 39.21 | K33: =ROUND(I33*J33/100,2) | L33: =I33+K33 | M33: =F33 | N33: =H33+K33 | O33: 2021 | P33: mensal
A34: 02/2021 | B34: ='Evolução RMI'!H26 | C34: 0 | D34: =B34-C34 | E34: 1.0906735 | F34: =ROUND(D34*E34,2) | G34: 0.7987 | H34: =ROUND(F34*G34/100,2) | I34: =F34+H34 | J34: 39.21 | K34: =ROUND(I34*J34/100,2) | L34: =I34+K34 | M34: =F34 | N34: =H34+K34 | O34: 2021 | P34: mensal
A35: 03/2021 | B35: ='Evolução RMI'!H27 | C35: 0 | D35: =B35-C35 | E35: 1.0818028 | F35: =ROUND(D35*E35,2) | G35: 0.7987 | H35: =ROUND(F35*G35/100,2) | I35: =F35+H35 | J35: 39.21 | K35: =ROUND(I35*J35/100,2) | L35: =I35+K35 | M35: =F35 | N35: =H35+K35 | O35: 2021 | P35: mensal
A36: 04/2021 | B36: ='Evolução RMI'!H28 | C36: 0 | D36: =B36-C36 | E36: 1.0725786 | F36: =ROUND(D36*E36,2) | G36: 0.7987 | H36: =ROUND(F36*G36/100,2) | I36: =F36+H36 | J36: 39.21 | K36: =ROUND(I36*J36/100,2) | L36: =I36+K36 | M36: =F36 | N36: =H36+K36 | O36: 2021 | P36: mensal
A37: 05/2021 | B37: ='Evolução RMI'!H29 | C37: 0 | D37: =B37-C37 | E37: 1.0685182 | F37: =ROUND(D37*E37,2) | G37: 0.7987 | H37: =ROUND(F37*G37/100,2) | I37: =F37+H37 | J37: 39.21 | K37: =ROUND(I37*J37/100,2) | L37: =I37+K37 | M37: =F37 | N37: =H37+K37 | O37: 2021 | P37: mensal
A38: 13º | B38: =TRUNC('Evolução RMI'!F29/2,2) | C38: 0 | D38: =B38-C38 | E38: 1.0685182 | F38: =ROUND(D38*E38,2) | G38: 0.7987 | H38: =ROUND(F38*G38/100,2) | I38: =F38+H38 | J38: 39.21 | K38: =ROUND(I38*J38/100,2) | L38: =I38+K38 | M38: =F38 | N38: =H38+K38 | O38: 2021 | P38: 13º
A39: 06/2021 | B39: ='Evolução RMI'!H30 | C39: 0 | D39: =B39-C39 | E39: 1.058358 | F39: =ROUND(D39*E39,2) | G39: 0.7987 | H39: =ROUND(F39*G39/100,2) | I39: =F39+H39 | J39: 39.21 | K39: =ROUND(I39*J39/100,2) | L39: =I39+K39 | M39: =F39 | N39: =H39+K39 | O39: 2021 | P39: mensal
A40: 13º | B40: =TRUNC('Evolução RMI'!F30*12/12-'Evolução RMI'!F29/2,2) | C40: 0 | D40: =B40-C40 | E40: 1.058358 | F40: =ROUND(D40*E40,2) | G40: 0.7987 | H40: =ROUND(F40*G40/100,2) | I40: =F40+H40 | J40: 39.21 | K40: =ROUND(I40*J40/100,2) | L40: =I40+K40 | M40: =F40 | N40: =H40+K40 | O40: 2021 | P40: 13º
A41: 07/2021 | B41: ='Evolução RMI'!H31 | C41: 0 | D41: =B41-C41 | E41: 1.0520457 | F41: =ROUND(D41*E41,2) | G41: 0.7987 | H41: =ROUND(F41*G41/100,2) | I41: =F41+H41 | J41: 39.21 | K41: =ROUND(I41*J41/100,2) | L41: =I41+K41 | M41: =F41 | N41: =H41+K41 | O41: 2021 | P41: mensal
A42: 08/2021 | B42: ='Evolução RMI'!H32 | C42: 0 | D42: =B42-C42 | E42: 1.0414232 | F42: =ROUND(D42*E42,2) | G42: 0.7987 | H42: =ROUND(F42*G42/100,2) | I42: =F42+H42 | J42: 39.21 | K42: =ROUND(I42*J42/100,2) | L42: =I42+K42 | M42: =F42 | N42: =H42+K42 | O42: 2021 | P42: mensal
A43: 09/2021 | B43: ='Evolução RMI'!H33 | C43: 0 | D43: =B43-C43 | E43: 1.0323386 | F43: =ROUND(D43*E43,2) | G43: 0.7987 | H43: =ROUND(F43*G43/100,2) | I43: =F43+H43 | J43: 39.21 | K43: =ROUND(I43*J43/100,2) | L43: =I43+K43 | M43: =F43 | N43: =H43+K43 | O43: 2021 | P43: mensal
A44: 10/2021 | B44: ='Evolução RMI'!H34 | C44: 0 | D44: =B44-C44 | E44: 1.0200974 | F44: =ROUND(D44*E44,2) | G44: 0.7987 | H44: =ROUND(F44*G44/100,2) | I44: =F44+H44 | J44: 39.21 | K44: =ROUND(I44*J44/100,2) | L44: =I44+K44 | M44: =F44 | N44: =H44+K44 | O44: 2021 | P44: mensal
A45: 11/2021 | B45: ='Evolução RMI'!H35 | C45: 0 | D45: =B45-C45 | E45: 1.0084 | F45: =ROUND(D45*E45,2) | G45: 0.4412 | H45: =ROUND(F45*G45/100,2) | I45: =F45+H45 | J45: 39.21 | K45: =ROUND(I45*J45/100,2) | L45: =I45+K45 | M45: =F45 | N45: =H45+K45 | O45: 2021 | P45: mensal
A46: 12/2021 | B46: ='Evolução RMI'!H36 | C46: 0 | D46: =B46-C46 | E46: 1 | F46: =ROUND(D46*E46,2) | G46: 0 | H46: =ROUND(F46*G46/100,2) | I46: =F46+H46 | J46: 39.21 | K46: =ROUND(I46*J46/100,2) | L46: =I46+K46 | M46: =F46 | N46: =H46+K46 | O46: 2021 | P46: mensal
A47: 01/2022 | B47: ='Evolução RMI'!H37 | C47: 0 | D47: =B47-C47 | E47: 1 | F47: =ROUND(D47*E47,2) | G47: 0 | H47: =ROUND(F47*G47/100,2) | I47: =F47+H47 | J47: 38.44 | K47: =ROUND(I47*J47/100,2) | L47: =I47+K47 | M47: =F47 | N47: =H47+K47 | O47: 2022 | P47: mensal
A48: 02/2022 | B48: ='Evolução RMI'!H38 | C48: 0 | D48: =B48-C48 | E48: 1 | F48: =ROUND(D48*E48,2) | G48: 0 | H48: =ROUND(F48*G48/100,2) | I48: =F48+H48 | J48: 37.71 | K48: =ROUND(I48*J48/100,2) | L48: =I48+K48 | M48: =F48 | N48: =H48+K48 | O48: 2022 | P48: mensal
A49: 03/2022 | B49: ='Evolução RMI'!H39 | C49: 0 | D49: =B49-C49 | E49: 1 | F49: =ROUND(D49*E49,2) | G49: 0 | H49: =ROUND(F49*G49/100,2) | I49: =F49+H49 | J49: 36.95 | K49: =ROUND(I49*J49/100,2) | L49: =I49+K49 | M49: =F49 | N49: =H49+K49 | O49: 2022 | P49: mensal
A50: 04/2022 | B50: ='Evolução RMI'!H40 | C50: 0 | D50: =B50-C50 | E50: 1 | F50: =ROUND(D50*E50,2) | G50: 0 | H50: =ROUND(F50*G50/100,2) | I50: =F50+H50 | J50: 36.02 | K50: =ROUND(I50*J50/100,2) | L50: =I50+K50 | M50: =F50 | N50: =H50+K50 | O50: 2022 | P50: mensal
A51: 13º | B51: =TRUNC('Evolução RMI'!F40/2,2) | C51: 0 | D51: =B51-C51 | E51: 1 | F51: =ROUND(D51*E51,2) | G51: 0 | H51: =ROUND(F51*G51/100,2) | I51: =F51+H51 | J51: 36.02 | K51: =ROUND(I51*J51/100,2) | L51: =I51+K51 | M51: =F51 | N51: =H51+K51 | O51: 2022 | P51: 13º
A52: 05/2022 | B52: ='Evolução RMI'!H41 | C52: 0 | D52: =B52-C52 | E52: 1 | F52: =ROUND(D52*E52,2) | G52: 0 | H52: =ROUND(F52*G52/100,2) | I52: =F52+H52 | J52: 35.19 | K52: =ROUND(I52*J52/100,2) | L52: =I52+K52 | M52: =F52 | N52: =H52+K52 | O52: 2022 | P52: mensal
A53: 13º | B53: =TRUNC('Evolução RMI'!F41*12/12-'Evolução RMI'!F40/2,2) | C53: 0 | D53: =B53-C53 | E53: 1 | F53: =ROUND(D53*E53,2) | G53: 0 | H53: =ROUND(F53*G53/100,2) | I53: =F53+H53 | J53: 35.19 | K53: =ROUND(I53*J53/100,2) | L53: =I53+K53 | M53: =F53 | N53: =H53+K53 | O53: 2022 | P53: 13º
A54: 06/2022 | B54: ='Evolução RMI'!H42 | C54: 0 | D54: =B54-C54 | E54: 1 | F54: =ROUND(D54*E54,2) | G54: 0 | H54: =ROUND(F54*G54/100,2) | I54: =F54+H54 | J54: 34.16 | K54: =ROUND(I54*J54/100,2) | L54: =I54+K54 | M54: =F54 | N54: =H54+K54 | O54: 2022 | P54: mensal
A55: 07/2022 | B55: ='Evolução RMI'!H43 | C55: 0 | D55: =B55-C55 | E55: 1 | F55: =ROUND(D55*E55,2) | G55: 0 | H55: =ROUND(F55*G55/100,2) | I55: =F55+H55 | J55: 33.14 | K55: =ROUND(I55*J55/100,2) | L55: =I55+K55 | M55: =F55 | N55: =H55+K55 | O55: 2022 | P55: mensal
A56: 08/2022 | B56: ='Evolução RMI'!H44 | C56: 0 | D56: =B56-C56 | E56: 1 | F56: =ROUND(D56*E56,2) | G56: 0 | H56: =ROUND(F56*G56/100,2) | I56: =F56+H56 | J56: 32.11 | K56: =ROUND(I56*J56/100,2) | L56: =I56+K56 | M56: =F56 | N56: =H56+K56 | O56: 2022 | P56: mensal
A57: 09/2022 | B57: ='Evolução RMI'!H45 | C57: 0 | D57: =B57-C57 | E57: 1 | F57: =ROUND(D57*E57,2) | G57: 0 | H57: =ROUND(F57*G57/100,2) | I57: =F57+H57 | J57: 30.94 | K57: =ROUND(I57*J57/100,2) | L57: =I57+K57 | M57: =F57 | N57: =H57+K57 | O57: 2022 | P57: mensal
A58: 10/2022 | B58: ='Evolução RMI'!H46 | C58: 0 | D58: =B58-C58 | E58: 1 | F58: =ROUND(D58*E58,2) | G58: 0 | H58: =ROUND(F58*G58/100,2) | I58: =F58+H58 | J58: 29.87 | K58: =ROUND(I58*J58/100,2) | L58: =I58+K58 | M58: =F58 | N58: =H58+K58 | O58: 2022 | P58: mensal
A59: 11/2022 | B59: ='Evolução RMI'!H47 | C59: 0 | D59: =B59-C59 | E59: 1 | F59: =ROUND(D59*E59,2) | G59: 0 | H59: =ROUND(F59*G59/100,2) | I59: =F59+H59 | J59: 28.85 | K59: =ROUND(I59*J59/100,2) | L59: =I59+K59 | M59: =F59 | N59: =H59+K59 | O59: 2022 | P59: mensal
A60: 12/2022 | B60: ='Evolução RMI'!H48 | C60: 0 | D60: =B60-C60 | E60: 1 | F60: =ROUND(D60*E60,2) | G60: 0 | H60: =ROUND(F60*G60/100,2) | I60: =F60+H60 | J60: 27.83 | K60: =ROUND(I60*J60/100,2) | L60: =I60+K60 | M60: =F60 | N60: =H60+K60 | O60: 2022 | P60: mensal
A61: 01/2023 | B61: ='Evolução RMI'!H49 | C61: 0 | D61: =B61-C61 | E61: 1 | F61: =ROUND(D61*E61,2) | G61: 0 | H61: =ROUND(F61*G61/100,2) | I61: =F61+H61 | J61: 26.71 | K61: =ROUND(I61*J61/100,2) | L61: =I61+K61 | M61: =F61 | N61: =H61+K61 | O61: 2023 | P61: mensal
A62: 02/2023 | B62: ='Evolução RMI'!H50 | C62: 0 | D62: =B62-C62 | E62: 1 | F62: =ROUND(D62*E62,2) | G62: 0 | H62: =ROUND(F62*G62/100,2) | I62: =F62+H62 | J62: 25.59 | K62: =ROUND(I62*J62/100,2) | L62: =I62+K62 | M62: =F62 | N62: =H62+K62 | O62: 2023 | P62: mensal
A63: 03/2023 | B63: ='Evolução RMI'!H51 | C63: 0 | D63: =B63-C63 | E63: 1 | F63: =ROUND(D63*E63,2) | G63: 0 | H63: =ROUND(F63*G63/100,2) | I63: =F63+H63 | J63: 24.67 | K63: =ROUND(I63*J63/100,2) | L63: =I63+K63 | M63: =F63 | N63: =H63+K63 | O63: 2023 | P63: mensal
A64: 04/2023 | B64: ='Evolução RMI'!H52 | C64: 0 | D64: =B64-C64 | E64: 1 | F64: =ROUND(D64*E64,2) | G64: 0 | H64: =ROUND(F64*G64/100,2) | I64: =F64+H64 | J64: 23.5 | K64: =ROUND(I64*J64/100,2) | L64: =I64+K64 | M64: =F64 | N64: =H64+K64 | O64: 2023 | P64: mensal
A65: 05/2023 | B65: ='Evolução RMI'!H53 | C65: 0 | D65: =B65-C65 | E65: 1 | F65: =ROUND(D65*E65,2) | G65: 0 | H65: =ROUND(F65*G65/100,2) | I65: =F65+H65 | J65: 22.58 | K65: =ROUND(I65*J65/100,2) | L65: =I65+K65 | M65: =F65 | N65: =H65+K65 | O65: 2023 | P65: mensal
A66: 13º | B66: =TRUNC('Evolução RMI'!F53/2,2) | C66: 0 | D66: =B66-C66 | E66: 1 | F66: =ROUND(D66*E66,2) | G66: 0 | H66: =ROUND(F66*G66/100,2) | I66: =F66+H66 | J66: 22.58 | K66: =ROUND(I66*J66/100,2) | L66: =I66+K66 | M66: =F66 | N66: =H66+K66 | O66: 2023 | P66: 13º
A67: 06/2023 | B67: ='Evolução RMI'!H54 | C67: 0 | D67: =B67-C67 | E67: 1 | F67: =ROUND(D67*E67,2) | G67: 0 | H67: =ROUND(F67*G67/100,2) | I67: =F67+H67 | J67: 21.46 | K67: =ROUND(I67*J67/100,2) | L67: =I67+K67 | M67: =F67 | N67: =H67+K67 | O67: 2023 | P67: mensal
A68: 13º | B68: =TRUNC('Evolução RMI'!F54*12/12-'Evolução RMI'!F53/2,2) | C68: 0 | D68: =B68-C68 | E68: 1 | F68: =ROUND(D68*E68,2) | G68: 0 | H68: =ROUND(F68*G68/100,2) | I68: =F68+H68 | J68: 21.46 | K68: =ROUND(I68*J68/100,2) | L68: =I68+K68 | M68: =F68 | N68: =H68+K68 | O68: 2023 | P68: 13º
A69: 07/2023 | B69: ='Evolução RMI'!H55 | C69: 0 | D69: =B69-C69 | E69: 1 | F69: =ROUND(D69*E69,2) | G69: 0 | H69: =ROUND(F69*G69/100,2) | I69: =F69+H69 | J69: 20.39 | K69: =ROUND(I69*J69/100,2) | L69: =I69+K69 | M69: =F69 | N69: =H69+K69 | O69: 2023 | P69: mensal
A70: 08/2023 | B70: ='Evolução RMI'!H56 | C70: 0 | D70: =B70-C70 | E70: 1 | F70: =ROUND(D70*E70,2) | G70: 0 | H70: =ROUND(F70*G70/100,2) | I70: =F70+H70 | J70: 19.32 | K70: =ROUND(I70*J70/100,2) | L70: =I70+K70 | M70: =F70 | N70: =H70+K70 | O70: 2023 | P70: mensal
A71: 09/2023 | B71: ='Evolução RMI'!H57 | C71: 0 | D71: =B71-C71 | E71: 1 | F71: =ROUND(D71*E71,2) | G71: 0 | H71: =ROUND(F71*G71/100,2) | I71: =F71+H71 | J71: 18.18 | K71: =ROUND(I71*J71/100,2) | L71: =I71+K71 | M71: =F71 | N71: =H71+K71 | O71: 2023 | P71: mensal
A72: 10/2023 | B72: ='Evolução RMI'!H58 | C72: 0 | D72: =B72-C72 | E72: 1 | F72: =ROUND(D72*E72,2) | G72: 0 | H72: =ROUND(F72*G72/100,2) | I72: =F72+H72 | J72: 17.21 | K72: =ROUND(I72*J72/100,2) | L72: =I72+K72 | M72: =F72 | N72: =H72+K72 | O72: 2023 | P72: mensal
A73: 11/2023 | B73: ='Evolução RMI'!H59 | C73: 0 | D73: =B73-C73 | E73: 1 | F73: =ROUND(D73*E73,2) | G73: 0 | H73: =ROUND(F73*G73/100,2) | I73: =F73+H73 | J73: 16.21 | K73: =ROUND(I73*J73/100,2) | L73: =I73+K73 | M73: =F73 | N73: =H73+K73 | O73: 2023 | P73: mensal
A74: 12/2023 | B74: ='Evolução RMI'!H60 | C74: 0 | D74: =B74-C74 | E74: 1 | F74: =ROUND(D74*E74,2) | G74: 0 | H74: =ROUND(F74*G74/100,2) | I74: =F74+H74 | J74: 15.29 | K74: =ROUND(I74*J74/100,2) | L74: =I74+K74 | M74: =F74 | N74: =H74+K74 | O74: 2023 | P74: mensal
A75: 01/2024 | B75: ='Evolução RMI'!H61 | C75: 0 | D75: =B75-C75 | E75: 1 | F75: =ROUND(D75*E75,2) | G75: 0 | H75: =ROUND(F75*G75/100,2) | I75: =F75+H75 | J75: 14.4 | K75: =ROUND(I75*J75/100,2) | L75: =I75+K75 | M75: =F75 | N75: =H75+K75 | O75: 2024 | P75: mensal
A76: 02/2024 | B76: ='Evolução RMI'!H62 | C76: 0 | D76: =B76-C76 | E76: 1 | F76: =ROUND(D76*E76,2) | G76: 0 | H76: =ROUND(F76*G76/100,2) | I76: =F76+H76 | J76: 13.43 | K76: =ROUND(I76*J76/100,2) | L76: =I76+K76 | M76: =F76 | N76: =H76+K76 | O76: 2024 | P76: mensal
A77: 03/2024 | B77: ='Evolução RMI'!H63 | C77: 0 | D77: =B77-C77 | E77: 1 | F77: =ROUND(D77*E77,2) | G77: 0 | H77: =ROUND(F77*G77/100,2) | I77: =F77+H77 | J77: 12.63 | K77: =ROUND(I77*J77/100,2) | L77: =I77+K77 | M77: =F77 | N77: =H77+K77 | O77: 2024 | P77: mensal
A78: 04/2024 | B78: ='Evolução RMI'!H64 | C78: 0 | D78: =B78-C78 | E78: 1 | F78: =ROUND(D78*E78,2) | G78: 0 | H78: =ROUND(F78*G78/100,2) | I78: =F78+H78 | J78: 11.8 | K78: =ROUND(I78*J78/100,2) | L78: =I78+K78 | M78: =F78 | N78: =H78+K78 | O78: 2024 | P78: mensal
A79: 13º | B79: =TRUNC('Evolução RMI'!F64/2,2) | C79: 0 | D79: =B79-C79 | E79: 1 | F79: =ROUND(D79*E79,2) | G79: 0 | H79: =ROUND(F79*G79/100,2) | I79: =F79+H79 | J79: 11.8 | K79: =ROUND(I79*J79/100,2) | L79: =I79+K79 | M79: =F79 | N79: =H79+K79 | O79: 2024 | P79: 13º
A80: 05/2024 | B80: ='Evolução RMI'!H65 | C80: 0 | D80: =B80-C80 | E80: 1 | F80: =ROUND(D80*E80,2) | G80: 0 | H80: =ROUND(F80*G80/100,2) | I80: =F80+H80 | J80: 10.91 | K80: =ROUND(I80*J80/100,2) | L80: =I80+K80 | M80: =F80 | N80: =H80+K80 | O80: 2024 | P80: mensal
A81: 13º | B81: =TRUNC('Evolução RMI'!F65*12/12-'Evolução RMI'!F64/2,2) | C81: 0 | D81: =B81-C81 | E81: 1 | F81: =ROUND(D81*E81,2) | G81: 0 | H81: =ROUND(F81*G81/100,2) | I81: =F81+H81 | J81: 10.91 | K81: =ROUND(I81*J81/100,2) | L81: =I81+K81 | M81: =F81 | N81: =H81+K81 | O81: 2024 | P81: 13º
A82: 06/2024 | B82: ='Evolução RMI'!H66 | C82: 0 | D82: =B82-C82 | E82: 1 | F82: =ROUND(D82*E82,2) | G82: 0 | H82: =ROUND(F82*G82/100,2) | I82: =F82+H82 | J82: 10.08 | K82: =ROUND(I82*J82/100,2) | L82: =I82+K82 | M82: =F82 | N82: =H82+K82 | O82: 2024 | P82: mensal
A83: 07/2024 | B83: ='Evolução RMI'!H67 | C83: 0 | D83: =B83-C83 | E83: 1 | F83: =ROUND(D83*E83,2) | G83: 0 | H83: =ROUND(F83*G83/100,2) | I83: =F83+H83 | J83: 9.29 | K83: =ROUND(I83*J83/100,2) | L83: =I83+K83 | M83: =F83 | N83: =H83+K83 | O83: 2024 | P83: mensal
A84: 08/2024 | B84: ='Evolução RMI'!H68 | C84: 0 | D84: =B84-C84 | E84: 1 | F84: =ROUND(D84*E84,2) | G84: 0 | H84: =ROUND(F84*G84/100,2) | I84: =F84+H84 | J84: 8.38 | K84: =ROUND(I84*J84/100,2) | L84: =I84+K84 | M84: =F84 | N84: =H84+K84 | O84: 2024 | P84: mensal
A85: 09/2024 | B85: ='Evolução RMI'!H69 | C85: 0 | D85: =B85-C85 | E85: 1 | F85: =ROUND(D85*E85,2) | G85: 0 | H85: =ROUND(F85*G85/100,2) | I85: =F85+H85 | J85: 7.51 | K85: =ROUND(I85*J85/100,2) | L85: =I85+K85 | M85: =F85 | N85: =H85+K85 | O85: 2024 | P85: mensal
A86: 10/2024 | B86: ='Evolução RMI'!H70 | C86: 0 | D86: =B86-C86 | E86: 1 | F86: =ROUND(D86*E86,2) | G86: 0 | H86: =ROUND(F86*G86/100,2) | I86: =F86+H86 | J86: 6.67 | K86: =ROUND(I86*J86/100,2) | L86: =I86+K86 | M86: =F86 | N86: =H86+K86 | O86: 2024 | P86: mensal
A87: 11/2024 | B87: ='Evolução RMI'!H71 | C87: 0 | D87: =B87-C87 | E87: 1 | F87: =ROUND(D87*E87,2) | G87: 0 | H87: =ROUND(F87*G87/100,2) | I87: =F87+H87 | J87: 5.74 | K87: =ROUND(I87*J87/100,2) | L87: =I87+K87 | M87: =F87 | N87: =H87+K87 | O87: 2024 | P87: mensal
A88: 12/2024 | B88: ='Evolução RMI'!H72 | C88: 0 | D88: =B88-C88 | E88: 1 | F88: =ROUND(D88*E88,2) | G88: 0 | H88: =ROUND(F88*G88/100,2) | I88: =F88+H88 | J88: 4.95 | K88: =ROUND(I88*J88/100,2) | L88: =I88+K88 | M88: =F88 | N88: =H88+K88 | O88: 2024 | P88: mensal
A89: 01/2025 | B89: ='Evolução RMI'!H73 | C89: 0 | D89: =B89-C89 | E89: 1 | F89: =ROUND(D89*E89,2) | G89: 0 | H89: =ROUND(F89*G89/100,2) | I89: =F89+H89 | J89: 4.02 | K89: =ROUND(I89*J89/100,2) | L89: =I89+K89 | M89: =F89 | N89: =H89+K89 | O89: 2025 | P89: mensal
A90: 02/2025 | B90: ='Evolução RMI'!H74 | C90: 0 | D90: =B90-C90 | E90: 1 | F90: =ROUND(D90*E90,2) | G90: 0 | H90: =ROUND(F90*G90/100,2) | I90: =F90+H90 | J90: 3.01 | K90: =ROUND(I90*J90/100,2) | L90: =I90+K90 | M90: =F90 | N90: =H90+K90 | O90: 2025 | P90: mensal
A91: Totais: | B91: =SUM(B15:B90) | C91: =SUM(C15:C90) | D91: =SUM(D15:D90) | F91: =SUM(F15:F90) | H91: =SUM(H15:H90) | I91: =SUM(I15:I90) | K91: =SUM(K15:K90) | L91: =SUM(L15:L90) | M91: =SUM(M15:M90) | N91: =SUM(N15:N90)
A93: R.M.A.: | B93: ='Evolução RMI'!F77
A94: Nº de meses com diferenças: 65
A95: Tabela da Justiça Federal (previdenciário): ORTN 10/1964–02/1986; OTN 03/1986–01/1989; IPC 01/1989–02/1989; BTN 03/1989–03/1990; IPC 03/1990–02/1991; INPC 03/1991–12/1992; IRSM 01/1993–02/1994; URV 03/1994–06/1994; IPC-r 07/1994–06/1995; INPC 07/1995–04/1996; IGP-DI 05/1996–08/2006; INPC a partir de 09/2006.
A97: Cristiano da Silva Ottone OAB/MG 152.214

Sheet Honorários
A1: Cálculo dos Honorários
A2: Nome do Segurado: | B2: SEGURADO EXEMPLO | D2: NIT: | E2: 000.00000.00-0
A3: CPF: | B3: 000.000.000-00 | D3: Data de Nascimento: | E3: 13/08/1976
A4: Sexo: | B4: Masculino | D4: Nº do Benefício: | E4: 000.000.000-0
A5: Espécie do Benefício: | B5: 46 - Aposentadoria Especial | D5: Nº do Processo: | E5: 0000000-00.2021.4.01.3800
A6: Início do Benefício (DIB): | B6: 16/10/2019 | D6: Data da Atualização: | E6: 08/05/2025
A7: Ajuizamento: | B7: 21/01/2021 | D7: Data da Prescrição: | E7: 16/10/2019
A9: Honorários de | B9: ='Parâmetros'!$B$21 | C9: % sobre a base de cálculo atualizada e sobre os juros.
A11: Data | B11: Base de Cálculo | C11: Base de Cálculo Atualizada | D11: Juros Sobre a Base de Cálculo | E11: Base Atualizada + Juros | F11: Valor Calculado
A12: 10/2019 | B12: ='Diferenças'!D15 | C12: ='Diferenças'!M15 | D12: ='Diferenças'!N15 | E12: =C12+D12 | F12: =ROUND(E12*'Parâmetros'!$B$21/100,2)
A13: 11/2019 | B13: ='Diferenças'!D16 | C13: ='Diferenças'!M16 | D13: ='Diferenças'!N16 | E13: =C13+D13 | F13: =ROUND(E13*'Parâmetros'!$B$21/100,2)
A14: 12/2019 | B14: ='Diferenças'!D17 | C14: ='Diferenças'!M17 | D14: ='Diferenças'!N17 | E14: =C14+D14 | F14: =ROUND(E14*'Parâmetros'!$B$21/100,2)
A15: 13º | B15: ='Diferenças'!D18 | C15: ='Diferenças'!M18 | D15: ='Diferenças'!N18 | E15: =C15+D15 | F15: =ROUND(E15*'Parâmetros'!$B$21/100,2)
A16: 01/2020 | B16: ='Diferenças'!D19 | C16: ='Diferenças'!M19 | D16: ='Diferenças'!N19 | E16: =C16+D16 | F16: =ROUND(E16*'Parâmetros'!$B$21/100,2)
A17: 02/2020 | B17: ='Diferenças'!D20 | C17: ='Diferenças'!M20 | D17: ='Diferenças'!N20 | E17: =C17+D17 | F17: =ROUND(E17*'Parâmetros'!$B$21/100,2)
A18: 03/2020 | B18: ='Diferenças'!D21 | C18: ='Diferenças'!M21 | D18: ='Diferenças'!N21 | E18: =C18+D18 | F18: =ROUND(E18*'Parâmetros'!$B$21/100,2)
A19: 04/2020 | B19: ='Diferenças'!D22 | C19: ='Diferenças'!M22 | D19: ='Diferenças'!N22 | E19: =C19+D19 | F19: =ROUND(E19*'Parâmetros'!$B$21/100,2)
A20: 13º | B20: ='Diferenças'!D23 | C20: ='Diferenças'!M23 | D20: ='Diferenças'!N23 | E20: =C20+D20 | F20: =ROUND(E20*'Parâmetros'!$B$21/100,2)
A21: 05/2020 | B21: ='Diferenças'!D24 | C21: ='Diferenças'!M24 | D21: ='Diferenças'!N24 | E21: =C21+D21 | F21: =ROUND(E21*'Parâmetros'!$B$21/100,2)
A22: 13º | B22: ='Diferenças'!D25 | C22: ='Diferenças'!M25 | D22: ='Diferenças'!N25 | E22: =C22+D22 | F22: =ROUND(E22*'Parâmetros'!$B$21/100,2)
A23: 06/2020 | B23: ='Diferenças'!D26 | C23: ='Diferenças'!M26 | D23: ='Diferenças'!N26 | E23: =C23+D23 | F23: =ROUND(E23*'Parâmetros'!$B$21/100,2)
... A87: 02/2025 | B87: ='Diferenças'!D90 | C87: ='Diferenças'!M90 | D87: ='Diferenças'!N90 | E87: =C87+D87 | F87: =ROUND(E87*'Parâmetros'!$B$21/100,2)
A88: Totais: | B88: =SUM(B12:B87) | C88: =SUM(C12:C87) | D88: =SUM(D12:D87) | E88: =SUM(E12:E87) | F88: =SUM(F12:F87)
A90: Sobre a Base Atualizada: | B90: =ROUND(C88*'Parâmetros'!$B$21/100,2)
A91: Sobre os Juros: | B91: =ROUND(D88*'Parâmetros'!$B$21/100,2)
A92: Valor Fixo: | B92: ='Parâmetros'!$B$23
A93: Total Geral de Honorários: | B93: =B90+B91+B92

Sheet IR (RRA)
A1: Informações para Imposto de Renda (Rendimentos Recebidos Acumuladamente)
A2: Nome do Segurado: | B2: SEGURADO EXEMPLO | D2: NIT: | E2: 000.00000.00-0
A3: CPF: | B3: 000.000.000-00 | D3: Data de Nascimento: | E3: 13/08/1976
A4: Sexo: | B4: Masculino | D4: Nº do Benefício: | E4: 000.000.000-0
A5: Espécie do Benefício: | B5: 46 - Aposentadoria Especial | D5: Nº do Processo: | E5: 0000000-00.2021.4.01.3800
A6: Início do Benefício (DIB): | B6: 16/10/2019 | D6: Data da Atualização: | E6: 08/05/2025
A7: Ajuizamento: | B7: 21/01/2021 | D7: Data da Prescrição: | E7: 16/10/2019
B9: Valor | C9: Meses
A10: Anos-base anteriores | B10: =SUMIFS('Diferenças'!$L$15:$L$90,'Diferenças'!$O$15:$O$90,"<2025") | C10: 69
A11: Ano-base atual (2025) | B11: =SUMIFS('Diferenças'!$L$15:$L$90,'Diferenças'!$O$15:$O$90,2025) | C11: 2
A12: Total | B12: =B10+B11 | C12: 71
A14: Meses: competências mensais + 1 mês por ano com 13º (art. 12-A da Lei 7.713/88).

Sheet Índices
A1: Índices mensais utilizados (%)
A3: Competência | B3: INPC | C3: JUROS MORA | D3: SELIC
A4: 10/2019 | B4: 0.04
A5: 11/2019 | B5: 0.54
A6: 12/2019 | B6: 1.22
A7: 01/2020 | B7: 0.19
A8: 02/2020 | B8: 0.17
A9: 03/2020 | B9: 0.18
A10: 04/2020 | B10: -0.23
A11: 05/2020 | B11: -0.25
A12: 06/2020 | B12: 0.3
A13: 07/2020 | B13: 0.44
A14: 08/2020 | B14: 0.36
A15: 09/2020 | B15: 0.87
... A27: 09/2021 | B27: 1.2
A28: 10/2021 | B28: 1.16 | C28: 0.3575
A29: 11/2021 | B29: 0.84 | C29: 0.4412
A30: 12/2021 | D30: 0.77
A31: 01/2022 | D31: 0.73
A32: 02/2022 | D32: 0.76
A33: 03/2022 | D33: 0.93
A34: 04/2022 | D34: 0.83
A35: 05/2022 | D35: 1.03
A36: 06/2022 | D36: 1.02
A37: 07/2022 | D37: 1.03
A38: 08/2022 | D38: 1.17
A39: 09/2022 | D39: 1.07
A40: 10/2022 | D40: 1.02
A41: 11/2022 | D41: 1.02
... A70: 04/2025 | D70: 1.06
A72: Fontes: IBGE/BCB-SGS (INPC 188, IGP-DI 190, IPCA-E 10764, SELIC 4390, meta SELIC 432) e Manual de Cálculos da Justiça Federal.
